openpibo_face_models/__init__.py
openpibo_face_models/models/age_net.caffemodel
openpibo_face_models/models/deploy_age.prototxt
openpibo_face_models/models/deploy_gender.prototxt
openpibo_face_models/models/emotion.tflite
openpibo_face_models/models/gender_net.caffemodel
openpibo_face_models/models/haarcascade_eye.xml
openpibo_face_models/models/haarcascade_frontalface_default.xml
openpibo_face_models-0.4.3.dist-info/METADATA
openpibo_face_models-0.4.3.dist-info/WHEEL
openpibo_face_models-0.4.3.dist-info/top_level.txt
openpibo_face_models-0.4.3.dist-info/RECORD
