Metadata-Version: 2.1
Name: openpibo-face-models
Version: 0.4.3
Summary: Models used by the openpibo-python package.
Home-page: https://github.com/themakerrobot/openpibo_face_models
Author: circulus
Author-email: leeyunjai@circul.us
License: UNKNOWN
Keywords: openpibo
Platform: UNKNOWN
Classifier: Natural Language :: English
Classifier: Programming Language :: Python :: 3.5
Classifier: Programming Language :: Python :: 3.6
Classifier: Programming Language :: Python :: 3.7
Classifier: Programming Language :: Python :: 3.8
